azdex/__init__.py
azdex/hyperliquid/__init__.py
azdex/hyperliquid/dex.py
azdex/py.typed
azdex-0.1.1.dist-info/WHEEL
azdex-0.1.1.dist-info/METADATA
azdex-0.1.1.dist-info/RECORD
