Metadata-Version: 2.3
Name: azdex
Version: 0.1.1
Summary: Add your description here
Keywords: python dex libs,dex,Python Decentralized Crypto Exchange Libs
Author: hhglory
Author-email: hhglory <hhglory@outlook.com>
Requires-Dist: hyperliquid-python-sdk>=0.18.0
Requires-Dist: loguru>=0.7.3
Requires-Python: >=3.12
